bioscrape/__init__.py
bioscrape/analysis.py
bioscrape/inference.cp310-win_amd64.pyd
bioscrape/inference.pxd
bioscrape/inference.pyx
bioscrape/inference_setup.py
bioscrape/lineage.cp310-win_amd64.pyd
bioscrape/pid_interfaces.py
bioscrape/random.cp310-win_amd64.pyd
bioscrape/random.pxd
bioscrape/random.pyx
bioscrape/sbmlutil.py
bioscrape/simulator.cp310-win_amd64.pyd
bioscrape/simulator.pxd
bioscrape/simulator.pyx
bioscrape/types.cp310-win_amd64.pyd
bioscrape/types.pxd
bioscrape/types.pyx
bioscrape/vector.pxd
Bioscrape-1.2.2.dist-info/LICENSE
Bioscrape-1.2.2.dist-info/METADATA
Bioscrape-1.2.2.dist-info/WHEEL
Bioscrape-1.2.2.dist-info/top_level.txt
Bioscrape-1.2.2.dist-info/RECORD
