Metadata-Version: 2.1
Name: Bioscrape
Version: 1.2.2
Summary: Biological Stochastic Simulation of Single Cell Reactions and Parameter Estimation
Author: Ayush Pandey, William Poole, Anandh Swaminathan
License: MIT License
Project-URL: Homepage, https://github.com/biocircuits/bioscrape/
Project-URL: Bug Tracker, https://github.com/biocircuits/bioscrape/issues
Keywords: SBML,synthetic biology,modeling,Chemical Reaction Network,CRN simulator,stochastic,parameter inference
Classifier: Development Status :: 5 - Production/Stable
Classifier: Intended Audience :: Science/Research
Classifier: License :: OSI Approved :: BSD License
Classifier: Programming Language :: Cython
Classifier: Programming Language :: Python
Classifier: Programming Language :: Python :: 3
Classifier: Programming Language :: Python :: 3.7
Classifier: Programming Language :: Python :: 3.8
Classifier: Programming Language :: Python :: 3.9
Classifier: Programming Language :: Python :: 3.10
Classifier: Topic :: Software Development
Classifier: Topic :: Scientific/Engineering
Classifier: Operating System :: OS Independent
Requires-Python: >=3.7
License-File: LICENSE
Requires-Dist: numpy
Requires-Dist: matplotlib
Requires-Dist: pytest
Requires-Dist: scipy
Requires-Dist: cython
Requires-Dist: python-libsbml
Requires-Dist: beautifulsoup4
Requires-Dist: sympy
Requires-Dist: emcee
Requires-Dist: pandas
Requires-Dist: corner
Requires-Dist: lmfit
Provides-Extra: test
Requires-Dist: pytest ; extra == 'test'
